akikm.py
akikm-0.0.2.dist-info/LICENSE
akikm-0.0.2.dist-info/METADATA
akikm-0.0.2.dist-info/WHEEL
akikm-0.0.2.dist-info/top_level.txt
akikm-0.0.2.dist-info/RECORD
