Metadata-Version: 2.1
Name: akikm
Version: 0.0.2
Summary: akikm
Home-page: https://github.com/aki/akikm
Author: aki
Author-email: heti@qq.com
License: BSD
Platform: UNKNOWN
Classifier: Programming Language :: Python :: 3
Classifier: Operating System :: OS Independent
Requires-Dist: python-dateutil (>=2.8.0)
Requires-Dist: pywin32 (>=227)
